siamese/__init__.py
siamese/builtins.py
siamese/core.py
siamese/engine.py
siamese/knowledge.py
siamese/resolver.py
siamese/unification.py
siamese_prototype-2.0.0.dist-info/METADATA
siamese_prototype-2.0.0.dist-info/WHEEL
siamese_prototype-2.0.0.dist-info/licenses/LICENSE
siamese_prototype-2.0.0.dist-info/RECORD
