Metadata-Version: 2.4
Name: siamese-prototype
Version: 2.0.0
Summary: A production-ready, asynchronous backward-chaining rule engine in Python.
Author-email: HsiangNianian <i@jyunko.cn>
License-File: LICENSE
Classifier: Framework :: AsyncIO
Classifier: License :: OSI Approved :: MIT License
Classifier: Operating System :: OS Independent
Classifier: Programming Language :: Python :: 3
Classifier: Topic :: Scientific/Engineering :: Artificial Intelligence
Requires-Python: >=3.11
Requires-Dist: aiohttp>=3.8.1
Requires-Dist: loguru>=0.6.0
Requires-Dist: pyyaml>=6.0
